telegram_monitor_ads/__init__.py
telegram_monitor_ads/config.py
telegram_monitor_ads/core.py
telegram_monitor_ads/exceptions.py
telegram_monitor_ads-1.0.3.dist-info/licenses/LICENSE
telegram_monitor_ads-1.0.3.dist-info/METADATA
telegram_monitor_ads-1.0.3.dist-info/WHEEL
telegram_monitor_ads-1.0.3.dist-info/top_level.txt
telegram_monitor_ads-1.0.3.dist-info/RECORD
