Metadata-Version: 2.4
Name: telegram-monitor-ads
Version: 1.0.3
Summary: TelegramMonitor广告管理模块
Author: 洛阳狼
Author-email: 洛阳狼 <hanwanlonga@gmail.com>
License: Proprietary
Classifier: Development Status :: 4 - Beta
Classifier: Intended Audience :: Developers
Classifier: Operating System :: OS Independent
Classifier: Programming Language :: Python :: 3
Classifier: Programming Language :: Python :: 3.8
Classifier: Programming Language :: Python :: 3.9
Classifier: Programming Language :: Python :: 3.10
Classifier: Programming Language :: Python :: 3.11
Classifier: Programming Language :: Python :: 3.12
Requires-Python: >=3.8
License-File: LICENSE
Requires-Dist: httpx>=0.24.0
Requires-Dist: python-dateutil>=2.8.0
Dynamic: author
Dynamic: license-file
Dynamic: requires-python
